cyberdockerutilstoto/__init__.py
cyberdockerutilstoto/docker_compose_down.py
cyberdockerutilstoto/docker_compose_pull_all.py
cyberdockerutilstoto/docker_compose_pull_restart.py
cyberdockerutilstoto/docker_compose_restart.py
cyberdockerutilstoto/library.py
cyberdockerutilstoto-0.2.dist-info/METADATA
cyberdockerutilstoto-0.2.dist-info/WHEEL
cyberdockerutilstoto-0.2.dist-info/top_level.txt
cyberdockerutilstoto-0.2.dist-info/RECORD
