Metadata-Version: 2.1
Name: cyberdockerutilstoto
Version: 0.2
Requires-Dist: PyYAML
